Metadata-Version: 2.1
Name: anubis
Version: 0.0.0
Summary: Astrophysical Nonparametrically Upgraded Bayesian Inference of Subpopulations
Home-page: https://github.com/sterinaldi/ANUBIS
Author: Stefano Rinaldi
Author-email: stefano.rinaldi@phd.unipi.it
License: UNKNOWN
Platform: UNKNOWN
Requires-Python: >=3.7
License-File: LICENSE
